{"fluid": "FLUT_crude_28", "coord_label": ["GOR", "P", "T"], "coord_unit": ["scf/stb", "bar", "K"], "prop_label": ["Ceq", "yAsp_V", "yAsp_L1", "yAsp_L2", "wtFrac_V", "wtFrac_L1", "wtFrac_L2", "volFrac_V", "volFrac_L1", "volFrac_L2", "dens_V", "dens_L1", "dens_L2", "dens_Asp", "SP_V", "SP_L1", "SP_L2", "SP_Asp", "visco_V", "visco_L1", "visco_L2"], "prop_unit": ["gAsp_L1/gAsp", "gAsp_V/g_V", "gAsp_L1/g_L1", "gAsp_L2/g_L2", "g_V/g", "g_L1/g", "g_L2/g", "cc_V/cc", "cc_L1/cc", "cc_L2/cc", "g/cc", "g/cc", "g/cc", "g/cc", "MPa^0.5", "MPa^0.5", "MPa^0.5", "MPa^0.5", "cP", "cP", "cP"], "GOR": [0.0], "P": [34.4738], "T": [623.15], "prop_table": [[[[0.65]]], [[[0.0]]], [[[0.042]]], [[[1.0]]], [[[0.0]]], [[[1.0]]], [[[0.0]]], [[[0.0]]], [[[1.0]]], [[[0.0]]], [[[0.0]]], [[[0.529]]], [[[0.575]]], [[[1.0]]], [[[0.0]]], [[[0.0]]], [[[0.0]]], [[[0.0]]], [[[0.0]]], [[[0.14]]], [[[0.0]]]]}